avatars/__init__.py
avatars/core/__init__.py
avatars/core/color.py
avatars/core/colors.py
avatars/core/seedrandom.py
avatars/sprite/__init__.py
avatars/sprite/base.py
avatars/sprite/avataaars/__init__.py
avatars/sprite/avatio/__init__.py
avatars/sprite/avatio/colors.py
avatars/sprite/avatio/paths.py
avatars/sprite/bottts/__init__.py
avatars/sprite/bottts/paths.py
avatars/sprite/female/__init__.py
avatars/sprite/gridy/__init__.py
avatars/sprite/human/__init__.py
avatars/sprite/identicon/__init__.py
avatars/sprite/initials/__init__.py
avatars/sprite/jdenticon/__init__.py
avatars/sprite/male/__init__.py
avatars-0.1.1.dist-info/LICENSE
avatars-0.1.1.dist-info/METADATA
avatars-0.1.1.dist-info/WHEEL
avatars-0.1.1.dist-info/top_level.txt
avatars-0.1.1.dist-info/RECORD
